abs_langchain_suite/__init__.py
abs_langchain_suite/cli.py
abs_langchain_suite/embeddings/__init__.py
abs_langchain_suite/embeddings/embedding_service.py
abs_langchain_suite/embeddings/vector_service.py
abs_langchain_suite/logging/db/base.py
abs_langchain_suite/logging/db/nosql_client.py
abs_langchain_suite/logging/db/sql_client.py
abs_langchain_suite/logging/pricing/service.py
abs_langchain_suite/logging/token_usage.py
abs_langchain_suite/provider/__init__.py
abs_langchain_suite/provider/azure_openai_provider.py
abs_langchain_suite/provider/base_provider.py
abs_langchain_suite/provider/claude_provider.py
abs_langchain_suite/provider/openai_provider.py
abs_langchain_suite/provider/provider_factory.py
abs_langchain_suite/schemas/__init__.py
abs_langchain_suite/schemas/embedding_config_schema.py
abs_langchain_suite/schemas/vector_config_schema.py
abs_langchain_suite/services/__init__.py
abs_langchain_suite/services/embedding_hooks_service.py
abs_langchain_suite/services/rag_service.py
abs_langchain_suite-0.3.1.dist-info/METADATA
abs_langchain_suite-0.3.1.dist-info/WHEEL
abs_langchain_suite-0.3.1.dist-info/entry_points.txt
abs_langchain_suite-0.3.1.dist-info/RECORD
