Metadata-Version: 2.3
Name: abs-langchain-suite
Version: 0.3.1
Summary: LangChain utilities with token tracking, RAG, and agent support
License: MIT
Author: AutoBridgeSystems
Author-email: info@autobridgesystems.com
Requires-Python: >=3.11,<4.0
Classifier: License :: OSI Approved :: MIT License
Classifier: Programming Language :: Python :: 3
Classifier: Programming Language :: Python :: 3.11
Classifier: Programming Language :: Python :: 3.12
Classifier: Programming Language :: Python :: 3.13
Requires-Dist: abs-exception-core (>=0.2.0,<0.3.0)
Requires-Dist: anthropic (>=0.57.1,<0.58.0)
Requires-Dist: azure-cosmos (>=4.9.0,<5.0.0)
Requires-Dist: faiss-cpu (>=1.11.0,<2.0.0)
Requires-Dist: langchain (>=0.3.25)
Requires-Dist: langchain-anthropic (>=0.3.17,<0.4.0)
Requires-Dist: langchain-community (>=0.0.10)
Requires-Dist: langchain-core (>=0.3.60)
Requires-Dist: langchain-openai (>=0.0.2)
Requires-Dist: langgraph (>=0.6.0,<0.7.0)
Requires-Dist: openai (>=1.10.0)
Requires-Dist: pydantic (>=2.0.0,<3.0.0)
Requires-Dist: pytest (>=8.4.1,<9.0.0)
Requires-Dist: pytest-asyncio (>=1.0.0,<2.0.0)
Requires-Dist: sqlalchemy (>=2.0.0,<3.0.0)
